JavaKaiyuanXiangmuZhongwenWendang20160820/README.md
JavaKaiyuanXiangmuZhongwenWendang20160820/__init__.py
JavaKaiyuanXiangmuZhongwenWendang20160820/__main__.py
JavaKaiyuanXiangmuZhongwenWendang20160820/file.epub
JavaKaiyuanXiangmuZhongwenWendang20160820/index.html
JavaKaiyuanXiangmuZhongwenWendang20160820/css/__init__.py
JavaKaiyuanXiangmuZhongwenWendang20160820/css/annotations.css
JavaKaiyuanXiangmuZhongwenWendang20160820/css/main.css
JavaKaiyuanXiangmuZhongwenWendang20160820/css/normalize.css
JavaKaiyuanXiangmuZhongwenWendang20160820/css/popup.css
JavaKaiyuanXiangmuZhongwenWendang20160820/font/__init__.py
JavaKaiyuanXiangmuZhongwenWendang20160820/font/fontello.eot
JavaKaiyuanXiangmuZhongwenWendang20160820/font/fontello.svg
JavaKaiyuanXiangmuZhongwenWendang20160820/font/fontello.ttf
JavaKaiyuanXiangmuZhongwenWendang20160820/font/fontello.woff
JavaKaiyuanXiangmuZhongwenWendang20160820/img/__init__.py
JavaKaiyuanXiangmuZhongwenWendang20160820/img/annotator-glyph-sprite.png
JavaKaiyuanXiangmuZhongwenWendang20160820/img/annotator-icon-sprite.png
JavaKaiyuanXiangmuZhongwenWendang20160820/img/apple-touch-icon.png
JavaKaiyuanXiangmuZhongwenWendang20160820/img/cancelfullscreen.png
JavaKaiyuanXiangmuZhongwenWendang20160820/img/close.png
JavaKaiyuanXiangmuZhongwenWendang20160820/img/fullscreen.png
JavaKaiyuanXiangmuZhongwenWendang20160820/img/loader.gif
JavaKaiyuanXiangmuZhongwenWendang20160820/img/menu-icon.png
JavaKaiyuanXiangmuZhongwenWendang20160820/img/save.png
JavaKaiyuanXiangmuZhongwenWendang20160820/img/saved.png
JavaKaiyuanXiangmuZhongwenWendang20160820/img/settings-s.png
JavaKaiyuanXiangmuZhongwenWendang20160820/img/settings.png
JavaKaiyuanXiangmuZhongwenWendang20160820/img/star.png
JavaKaiyuanXiangmuZhongwenWendang20160820/js/__init__.py
JavaKaiyuanXiangmuZhongwenWendang20160820/js/epub.js
JavaKaiyuanXiangmuZhongwenWendang20160820/js/epub.min.js
JavaKaiyuanXiangmuZhongwenWendang20160820/js/epub.min.map
JavaKaiyuanXiangmuZhongwenWendang20160820/js/hooks.min.js
java_kaiyuan_xiangmu_zhongwen_wendang_20160820-2024.3.2.0.dist-info/METADATA
java_kaiyuan_xiangmu_zhongwen_wendang_20160820-2024.3.2.0.dist-info/WHEEL
java_kaiyuan_xiangmu_zhongwen_wendang_20160820-2024.3.2.0.dist-info/entry_points.txt
java_kaiyuan_xiangmu_zhongwen_wendang_20160820-2024.3.2.0.dist-info/top_level.txt
java_kaiyuan_xiangmu_zhongwen_wendang_20160820-2024.3.2.0.dist-info/RECORD
